typed_app_settings/__init__.py
typed_app_settings/_get_annotations.py
typed_app_settings/_lib.py
typed_app_settings/py.typed
typed_app_settings-0.4.dist-info/licenses/LICENSE
typed_app_settings-0.4.dist-info/WHEEL
typed_app_settings-0.4.dist-info/METADATA
typed_app_settings-0.4.dist-info/RECORD
