Metadata-Version: 2.4
Name: typed_app_settings
Version: 0.4
Summary: A package to create and use app specific settings with type hints.
Author-email: Thomas Krapp <t.krapp@gmail.com>
Requires-Python: >=3.9
Classifier: License :: OSI Approved :: MIT License
Classifier: Environment :: Web Environment
Classifier: Framework :: Django
Classifier: Framework :: Django :: 3.0
Classifier: Framework :: Django :: 3.1
Classifier: Framework :: Django :: 3.2
Classifier: Framework :: Django :: 4.0
Classifier: Intended Audience :: Developers
Classifier: Operating System :: OS Independent
Classifier: Programming Language :: Python
Classifier: Programming Language :: Python :: 3.8
Classifier: Programming Language :: Python :: 3.9
Classifier: Programming Language :: Python :: 3.10
Classifier: Topic :: Software Development :: Libraries :: Python Modules
Classifier: Development Status :: 3 - Alpha
License-File: LICENSE
Requires-Dist: Django >= 3.0
Requires-Dist: black ; extra == "dev"
Project-URL: Home, https://github.com/tkrapp/django-typed-app-settings
Provides-Extra: dev
